imgdata
